difnn/AutoTMModel.py
difnn/Autoformer.py
difnn/Crossformer.py
difnn/DLinear.py
difnn/DifnnModel.py
difnn/ETSformer.py
difnn/FEDformer.py
difnn/FiLM.py
difnn/FreTS.py
difnn/Informer.py
difnn/Koopa.py
difnn/LightTS.py
difnn/MICN.py
difnn/Mamba.py
difnn/MambaSimple.py
difnn/Math.py
difnn/Model.py
difnn/Nonstationary_Transformer.py
difnn/PAttn.py
difnn/PatchTST.py
difnn/Pyraformer.py
difnn/Reformer.py
difnn/SCINet.py
difnn/SegRNN.py
difnn/TSMixer.py
difnn/TemporalFusionTransformer.py
difnn/TiDE.py
difnn/TimeMixer.py
difnn/TimeXer.py
difnn/TimesNet.py
difnn/Transformer.py
difnn/__init__.py
difnn/autotm_utility.cp312-win_amd64.pyd
difnn/autotm_utility.cpython-310-x86_64-linux-gnu.so
difnn/difnn_utility.cp312-win_amd64.pyd
difnn/difnn_utility.cpython-310-x86_64-linux-gnu.so
difnn/forecast_utility.cp312-win_amd64.pyd
difnn/forecast_utility.cpython-310-x86_64-linux-gnu.so
difnn/iTransformer.py
difnn-2.2.11.dist-info/METADATA
difnn-2.2.11.dist-info/WHEEL
difnn-2.2.11.dist-info/entry_points.txt
difnn-2.2.11.dist-info/top_level.txt
difnn-2.2.11.dist-info/RECORD
