Metadata-Version: 2.1
Name: difnn
Version: 2.2.11
Summary: difnn
Home-page: UNKNOWN
Author: Forecaster
License: UNKNOWN
Platform: UNKNOWN
Classifier: Programming Language :: Python :: 3
Classifier: License :: OSI Approved :: MIT License
Classifier: Operating System :: OS Independent
Requires-Python: >=3.7
